abspy.cpython-39-aarch64-linux-gnu.so
abs/__init__.py
abs/cli.py
abs/curve.py
abs/part_processor.py
abs/sampler.py
abs/shape.py
abs/surface.py
abs/topology.py
abs/utils.py
abs/winding_number.py
include/eigen-src/.gitignore
include/eigen-src/.gitlab-ci.yml
include/eigen-src/.hgeol
include/eigen-src/CMakeLists.txt
include/eigen-src/COPYING.APACHE
include/eigen-src/COPYING.BSD
include/eigen-src/COPYING.GPL
include/eigen-src/COPYING.LGPL
include/eigen-src/COPYING.MINPACK
include/eigen-src/COPYING.MPL2
include/eigen-src/COPYING.README
include/eigen-src/CTestConfig.cmake
include/eigen-src/CTestCustom.cmake.in
include/eigen-src/INSTALL
include/eigen-src/README.md
include/eigen-src/eigen3.pc.in
include/eigen-src/signature_of_eigen3_matrix_library
include/eigen-src/.gitlab/issue_templates/Bug Report.md
include/eigen-src/.gitlab/issue_templates/Feature Request.md
include/eigen-src/.gitlab/merge_request_templates/Merge Request Template.md
include/eigen-src/Eigen/Cholesky
include/eigen-src/Eigen/CholmodSupport
include/eigen-src/Eigen/Core
include/eigen-src/Eigen/Dense
include/eigen-src/Eigen/Eigen
include/eigen-src/Eigen/Eigenvalues
include/eigen-src/Eigen/Geometry
include/eigen-src/Eigen/Householder
include/eigen-src/Eigen/IterativeLinearSolvers
include/eigen-src/Eigen/Jacobi
include/eigen-src/Eigen/KLUSupport
include/eigen-src/Eigen/LU
include/eigen-src/Eigen/MetisSupport
include/eigen-src/Eigen/OrderingMethods
include/eigen-src/Eigen/PaStiXSupport
include/eigen-src/Eigen/PardisoSupport
include/eigen-src/Eigen/QR
include/eigen-src/Eigen/QtAlignedMalloc
include/eigen-src/Eigen/SPQRSupport
include/eigen-src/Eigen/SVD
include/eigen-src/Eigen/Sparse
include/eigen-src/Eigen/SparseCholesky
include/eigen-src/Eigen/SparseCore
include/eigen-src/Eigen/SparseLU
include/eigen-src/Eigen/SparseQR
include/eigen-src/Eigen/StdDeque
include/eigen-src/Eigen/StdList
include/eigen-src/Eigen/StdVector
abs_hdf5-0.2.3.dist-info/METADATA
abs_hdf5-0.2.3.dist-info/WHEEL
abs_hdf5-0.2.3.dist-info/entry_points.txt
abs_hdf5-0.2.3.dist-info/RECORD
abs_hdf5-0.2.3.dist-info/licenses/AUTHORS.rst
abs_hdf5-0.2.3.dist-info/licenses/LICENSE-MIT
abs_hdf5-0.2.3.dist-info/licenses/LICENSE-MPL-2.0
