Metadata-Version: 2.2
Name: abs-hdf5
Version: 0.2.3
Summary: A Python + C++ toolkit for reading CAD B-Rep data from HDF5, sampling surfaces/curves, and generating blue-noise point clouds.
Keywords: CAD,geometry,sampling,blue-noise,hdf5
Author-Email: "Sai Chandra Madduri, Nafiseh Izadyar, Teseo Schneider" <teseo@uvic.ca>
License: MIT
Classifier: License :: OSI Approved :: MIT License
Classifier: License :: OSI Approved :: Mozilla Public License 2.0 (MPL 2.0)
Classifier: Programming Language :: C++
Classifier: Programming Language :: Python :: 3
Classifier: Programming Language :: Python :: 3.8
Classifier: Operating System :: OS Independent
Requires-Python: >=3.8
Requires-Dist: numpy
Requires-Dist: scipy
Requires-Dist: h5py
Requires-Dist: geomdl
Requires-Dist: tqdm
Requires-Dist: joblib
Requires-Dist: meshio
